{"name": "Initialize Culture Experiment & Saturate Cultures", "category": "Induction - High Throughput", "inputs": [{"name": "Culture Condition", "part": null, "array": true, "routing": null}, {"name": "Temperature (\u00b0C)", "part": null, "array": null, "routing": null}, {"name": "Prepare Experimental Media now?", "part": null, "array": null, "routing": null}, {"name": "Kanamycin Concentration (\u00b5g/mL)", "part": null, "array": null, "routing": null}, {"name": "Chloramphenicol Concentration (\u00b5g/mL)", "part": null, "array": null, "routing": null}], "outputs": [{"name": "Overnight Experimental Prep Plate", "part": null, "array": true, "routing": "p"}], "on_the_fly": null}